MANIFEST.in
README.rst
setup.py
version.txt
bin/charon_ast_hash
charon/__init__.py
charon/codec.c
charon/codec.py
charon/codec_registry.c
charon/codec_registry.py
charon/types.py
charon/extensions/__init__.py
charon/extensions/standard_registry.c
charon/extensions/standard_registry.py
charon/testing/__init__.py
charon/testing/ast_hash.py
charon/testing/generic.py
charon/testing/metatest.py
ql_charon.egg-info/PKG-INFO
ql_charon.egg-info/SOURCES.txt
ql_charon.egg-info/dependency_links.txt
ql_charon.egg-info/requires.txt
ql_charon.egg-info/top_level.txt