Metadata-Version: 1.1
Name: ql-charon
Version: 2.1.2
Summary: Serialization library as a replacement for pickle
Home-page: https://github.com/qntln/charon
Author: Quantlane
Author-email: code@quantlane.com
License: UNKNOWN
Platform: UNKNOWN
Classifier: Development Status :: 4 - Beta
Classifier: License :: OSI Approved :: Apache Software License
Classifier: Natural Language :: English
Classifier: Programming Language :: Python :: 3 :: Only
Classifier: Programming Language :: Python :: 3.5
Classifier: Programming Language :: Python :: 3.6
